Workbook

Sheet Members Data
B3: Members Data
B7: Month | C7: Starting Members | D7: New Members | E7: Lost Members | F7: Active Members
B8: Jan | C8: 450 | D8: 45 | E8: 20 | F8: 475
B9: Feb | C9: 475 | D9: 42 | E9: 24 | F9: 493
B10: Mar | C10: 493 | D10: 38 | E10: 31 | F10: 500
B11: Apr | C11: 500 | D11: 35 | E11: 33 | F11: 502
B12: May | C12: 502 | D12: 40 | E12: 39 | F12: 503
B13: Jun | C13: 503 | D13: 37 | E13: 41 | F13: 499

Sheet Revenue Data
B3: Revenue Data
B7: Month | C7: Membership Revenue | D7: PT Revenue | E7: Supplements Revenue | F7: Total Revenue | G7: Marketing Spend
B8: Jan | C8: 29250 | D8: 4200 | E8: 950 | F8: 34400 | G8: 1200
B9: Feb | C9: 30420 | D9: 4350 | E9: 1020 | F9: 35790 | G9: 1250
B10: Mar | C10: 30875 | D10: 4520 | E10: 980 | F10: 36375 | G10: 1300
B11: Apr | C11: 31005 | D11: 4480 | E11: 960 | F11: 36445 | G11: 1350
B12: May | C12: 31070 | D12: 4600 | E12: 1010 | F12: 36680 | G12: 1400
B13: Jun | C13: 30810 | D13: 4510 | E13: 930 | F13: 36250 | G13: 1450

Sheet KPI Calculations
B3: KPI Calculations
B7: Month | C7: Churn Rate | D7: Retention Rate | E7: Revenue Growth % | F7: Revenue Per Member | G7: CAC | H7: CLV (12 months)
B8: Jan | C8: ='Members Data'!E8/'Members Data'!C8 -> 0.044444444 | D8: =('Members Data'!C8-'Members Data'!E8)/'Members Data'!C8 -> 0.95555556 | E8: - | F8: ='Revenue Data'!F8/'Members Data'!F8 -> 72.421053 | G8: ='Revenue Data'!G8/'Members Data'!D8 -> 26.666667 | H8: =F8*12 -> 869.05263
B9: Feb | C9: ='Members Data'!E9/'Members Data'!C9 -> 0.050526316 | D9: =('Members Data'!C9-'Members Data'!E9)/'Members Data'!C9 -> 0.94947368 | E9: =('Revenue Data'!F9-'Revenue Data'!F8)/'Revenue Data'!F8 -> 0.040406977 | F9: ='Revenue Data'!F9/'Members Data'!F9 -> 72.596349 | G9: ='Revenue Data'!G9/'Members Data'!D9 -> 29.761905 | H9: =F9*12 -> 871.15619
B10: Mar | C10: ='Members Data'!E10/'Members Data'!C10 -> 0.062880325 | D10: =('Members Data'!C10-'Members Data'!E10)/'Members Data'!C10 -> 0.93711968 | E10: =('Revenue Data'!F10-'Revenue Data'!F9)/'Revenue Data'!F9 -> 0.016345348 | F10: ='Revenue Data'!F10/'Members Data'!F10 -> 72.75 | G10: ='Revenue Data'!G10/'Members Data'!D10 -> 34.210526 | H10: =F10*12 -> 873
B11: Apr | C11: ='Members Data'!E11/'Members Data'!C11 -> 0.066 | D11: =('Members Data'!C11-'Members Data'!E11)/'Members Data'!C11 -> 0.934 | E11: =('Revenue Data'!F11-'Revenue Data'!F10)/'Revenue Data'!F10 -> 0.0019243986 | F11: ='Revenue Data'!F11/'Members Data'!F11 -> 72.599602 | G11: ='Revenue Data'!G11/'Members Data'!D11 -> 38.571429 | H11: =F11*12 -> 871.19522
B12: May | C12: ='Members Data'!E12/'Members Data'!C12 -> 0.077689243 | D12: =('Members Data'!C12-'Members Data'!E12)/'Members Data'!C12 -> 0.92231076 | E12: =('Revenue Data'!F12-'Revenue Data'!F11)/'Revenue Data'!F11 -> 0.0064480724 | F12: ='Revenue Data'!F12/'Members Data'!F12 -> 72.922465 | G12: ='Revenue Data'!G12/'Members Data'!D12 -> 35 | H12: =F12*12 -> 875.06958
B13: Jun | C13: ='Members Data'!E13/'Members Data'!C13 -> 0.081510934 | D13: =('Members Data'!C13-'Members Data'!E13)/'Members Data'!C13 -> 0.91848907 | E13: =('Revenue Data'!F13-'Revenue Data'!F12)/'Revenue Data'!F12 -> -0.01172301 | F13: ='Revenue Data'!F13/'Members Data'!F13 -> 72.645291 | G13: ='Revenue Data'!G13/'Members Data'!D13 -> 39.189189 | H13: =F13*12 -> 871.74349
C19: Comments
C21: Churn rate: | D21: 4.44% -> 8.15% | E21: Churn nearly doubled in six months.
D23: Meaning:
D25: retention deteriorated,
D26: customer satisfaction may be declining,
D27: operational issues may exist.
C30: Retention Trend: | D30: 95.56% -> 91.85% | E30: Fewer customers are staying with the business over time.
D32: Even a 3-4% drop in retention creates large revenue leakage.
C35: Revenue Per Member: | D35: £72.42 -> £72.65 | E35: Revenue per member remained flat.
D37: Meaning:
D39: weak upselling,
D40: limited monetisation growth,
D41: reliance on acquisition instead of member value expansion.
C44: CAC vs CLV: | F44: Customer acquisition remains highly profitable.
D45: CAC | E45: £25-£39
D46: CLV | E46: ~£870
D48: Meaning:
D50: marketing is not the issue,
D51: retention is the issue.
C58: Conclusion:
D60: The business continues to acquire members efficiently; however, increasing churn is offsetting growth and limiting revenue expansion. Retention should become the primary operational focus.

Sheet Dashboard
B4: Executive Insights Section
D13: Active Members | E13: Monthly Revenue | F13: Churn rate | G13: Retention rate | H13: Revenue per member
D14: 499 | E14: 36250 | F14: 0.0815 | G14: 0.9185 | H14: 72.65

Sheet Executive_Summary
B3: FITNESS CLUB PERFORMANCE ANALYSIS
B5: Business Performance Review
B6: January 2025 – June 2025
B8: Prepared by:
B9: Tudor Rusu
B10: Business Performance Analyst
D20: BUSINESS OBJECTIVE
D22: The purpose of this analysis is to evaluate membership performance, revenue trends, customer retention, and acquisition efficiency over a six-month period.
D24: The analysis aims to identify the key factors limiting revenue growth and provide data-driven recommendations to improve business performance.
D33: KEY FINDING #1 – INCREASING CUSTOMER CHURN
D35: Monthly churn increased from 4.44% in January to 8.15% in June.
D37: This represents an 83% increase in customer cancellations during the analysis period and indicates a significant deterioration in member retention.
D43: KEY FINDING #2 – MEMBERSHIP GROWTH HAS STALLED
D45: Active membership increased steadily during the first five months, reaching a peak of 503 members in May.
D47: However, membership growth stagnated during Q2 and declined to 499 members in June, suggesting that rising churn is beginning to offset new member acquisition.
D53: KEY FINDING #3 – REVENUE PER MEMBER REMAINED STABLE
D55: Average revenue per member remained relatively stable at approximately £72 throughout the analysis period.
D57: While this indicates consistent member spending behaviour, it also suggests limited success in increasing customer value through upselling initiatives such as personal training, premium memberships, or supplementary products.
... D146: • Revenue leakage estimates assume that current churn levels continue without intervention.
